SysInfo/SysInfo.py
SysInfo/__init__.py
SysInfo/main.py
sysinfo_dawidePl-1.1.2.dist-info/METADATA
sysinfo_dawidePl-1.1.2.dist-info/WHEEL
sysinfo_dawidePl-1.1.2.dist-info/top_level.txt
sysinfo_dawidePl-1.1.2.dist-info/RECORD
