Metadata-Version: 2.1
Name: sysinfo-dawidePl
Version: 1.1.2
Summary: Simple Linux command showing hardware usage data in nice form.
Home-page: https://github.com/dawidePl/Linux-SysInfo
Author: dawidePl
Author-email: dawidefirmowy@gmail.com
License: UNKNOWN
Project-URL: Bug Tracker, https://github.com/dawidePl/Linux-SysInfo/issues
Platform: UNKNOWN
Classifier: Programming Language :: Python :: 3
Classifier: License :: OSI Approved :: MIT License
Classifier: Operating System :: Unix
Classifier: Development Status :: 3 - Alpha
Requires-Python: <=3.6
